example_package_devforma/__init__.py
example_package_devforma/example.py
example_package_devforma-0.0.1.dist-info/LICENCE
example_package_devforma-0.0.1.dist-info/METADATA
example_package_devforma-0.0.1.dist-info/WHEEL
example_package_devforma-0.0.1.dist-info/top_level.txt
example_package_devforma-0.0.1.dist-info/RECORD
